bmondata/__init__.py
bmondata/schedule.py
bmondata/server.py
bmondata/util.py
bmondata-1.0.6.dist-info/LICENSE
bmondata-1.0.6.dist-info/METADATA
bmondata-1.0.6.dist-info/WHEEL
bmondata-1.0.6.dist-info/top_level.txt
bmondata-1.0.6.dist-info/RECORD
