Metadata-Version: 2.1
Name: bmondata
Version: 1.0.6
Summary: Allows retrieval and storage of data on BMON Servers.
Home-page: https://github.com/alanmitchell/bmondata
Author: Alan Mitchell
Author-email: tabb99@gmail.com
License: UNKNOWN
Platform: UNKNOWN
Classifier: Programming Language :: Python :: 3
Classifier: License :: OSI Approved :: Apache Software License
Classifier: Operating System :: OS Independent
Requires-Python: >=3.6
Requires-Dist: requests (>=2.18.4)
Requires-Dist: pandas (>=0.23.2)
